atlasutils/VFTables.py
atlasutils/__init__.py
atlasutils/addressparsing.py
atlasutils/ascii2binary.py
atlasutils/ascii2hex.py
atlasutils/ascii2octal.py
atlasutils/disassutils.py
atlasutils/emutils.py
atlasutils/envi_x86.py
atlasutils/enviutils.py
atlasutils/errno.py
atlasutils/hacklib.py
atlasutils/idafuncs.py
atlasutils/nc.py
atlasutils/nethelper.py
atlasutils/portscan.py
atlasutils/props.py
atlasutils/smartprint.py
atlasutils/urlencode.py
atlasutils/vwmerge.py
atlasutils/pdb/__init__.py
atlasutils/syscall/__init__.py
atlasutils/syscall/bsd.py
atlasutils/syscall/linux.py
atlasutils/visualutils/__init__.py
atlasutils/visualutils/layout-about-to-rehash-for-real-forces.py
atlasutils/visualutils/layout-backup-ITSALIVE.py
atlasutils/visualutils/layout-backup-StringOfPearls_and_SnakeEffect.py
atlasutils/visualutils/layout-backup-forces-seem-almost-sane.py
atlasutils/visualutils/layout-backup-stuck-to-the-ground.py
atlasutils/visualutils/layout-something_sane.py
atlasutils/visualutils/layout-something_sane_n_pretty.py
atlasutils/visualutils/layout-with-pretty-edges-from-hell.py
atlasutils/visualutils/layout.py
atlasutils/visualutils/layout_with_autoCeiling.py
atlasutils/visualutils/testing.py
atlasutils/visualutils/viv.py
atlasutils/vivutils/__init__.py
atlasutils/vivutils/cppnamedemangle.py
atlasutils/vivutils/do_strings.py
atlasutils/vivutils/dumpfunc.py
atlasutils/vtraceutils/__init__.py
atlasutils/vtraceutils/heap.py
atlasutils/vtraceutils/tracebin.py
atlasutils-3.1.0.data/scripts/LiveOrganTransplant
atlasutils-3.1.0.data/scripts/LivePatch
atlasutils-3.1.0.data/scripts/ROT13.py
atlasutils-3.1.0.data/scripts/VulnCatcher.py
atlasutils-3.1.0.data/scripts/ascii2binary
atlasutils-3.1.0.data/scripts/ascii2hex
atlasutils-3.1.0.data/scripts/ascii2octal
atlasutils-3.1.0.data/scripts/binary2ascii
atlasutils-3.1.0.data/scripts/cclean
atlasutils-3.1.0.data/scripts/clusterServer
atlasutils-3.1.0.data/scripts/clusterWorker
atlasutils-3.1.0.data/scripts/dumpimports.py
atlasutils-3.1.0.dist-info/METADATA
atlasutils-3.1.0.dist-info/WHEEL
atlasutils-3.1.0.dist-info/top_level.txt
atlasutils-3.1.0.dist-info/RECORD
