Metadata-Version: 2.1
Name: atlasutils
Version: 3.1.0
Summary: atlas' hacking toolbelt full of toys
Home-page: https://github.com/atlas0fd00m/atlasutils
Author: atlas of d00m
Author-email: atlas@r4780y.com
License: UNKNOWN
Platform: UNKNOWN
